meshtastic2hass/__init__.py
meshtastic2hass/config.toml
meshtastic2hass/globals.py
meshtastic2hass/meshtastic2hass.py
meshtastic2hass-1.0.20.dist-info/licenses/LICENSE
meshtastic2hass-1.0.20.dist-info/METADATA
meshtastic2hass-1.0.20.dist-info/WHEEL
meshtastic2hass-1.0.20.dist-info/entry_points.txt
meshtastic2hass-1.0.20.dist-info/top_level.txt
meshtastic2hass-1.0.20.dist-info/RECORD
