Metadata-Version: 2.4
Name: meshtastic2hass
Version: 1.0.20
Summary: A Python client that connects Meshtastic radios via MQTT to Home Assistant (Hass).
Home-page: https://github.com/Mictronics/meshtastic2hass
Author: Michael Wolf
Author-email: michael@mictronics.de
License: GPL v3+
Platform: any
Classifier: Development Status :: 4 - Beta
Classifier: Programming Language :: Python
Requires-Python: >=3.8
License-File: LICENSE
Requires-Dist: importlib-metadata>=4.6.4
Requires-Dist: globals>=0.3.36
Requires-Dist: meshtastic>=2.3.14
Requires-Dist: paho-mqtt>=2.1.0
Requires-Dist: pypubsub>=0.1.2
Requires-Dist: tomlkit>=0.13.0
Provides-Extra: testing
Dynamic: license-file
